mutwo/csound_converters/__init__.py
mutwo/csound_converters/configurations.py
mutwo/csound_converters/constants.py
mutwo/csound_converters/csound.py
mutwo/csound_version/__init__.py
mutwo.csound-0.8.0.dist-info/LICENSE
mutwo.csound-0.8.0.dist-info/METADATA
mutwo.csound-0.8.0.dist-info/WHEEL
mutwo.csound-0.8.0.dist-info/top_level.txt
mutwo.csound-0.8.0.dist-info/RECORD
