Metadata-Version: 2.1
Name: mutwo.csound
Version: 0.8.0
Summary: csound extension for event based framework for generative art
Home-page: https://github.com/mutwo-org/mutwo.ext-csound
Author: Levin Eric Zimmermann
Author-email: levin.eric.zimmermann@posteo.eu
License: GPL
Project-URL: Documentation, https://mutwo-org.github.io
Requires-Python: >=3.10, <4
License-File: LICENSE
Requires-Dist: mutwo.core <3.0.0,>=2.0.0
Requires-Dist: natsort <9.0.0,>=8.0.0
Provides-Extra: testing
Requires-Dist: pytest >=7.1.1 ; extra == 'testing'
